aicosmos_client/__init__.py
aicosmos_client/client.py
aicosmos_client-0.0.14.dist-info/METADATA
aicosmos_client-0.0.14.dist-info/WHEEL
aicosmos_client-0.0.14.dist-info/licenses/LICENSE
aicosmos_client-0.0.14.dist-info/RECORD
