Metadata-Version: 2.4
Name: aicosmos_client
Version: 0.0.14
Summary: client for AICosmos platform
Project-URL: Homepage, https://github.com/TitiSkywalker/AICosmos-Client
Project-URL: Issues, https://github.com/TitiSkywalker/AICosmos-Client/issues
Author-email: Example Author <author@example.com>
License-Expression: MIT
License-File: LICENSE
Classifier: Operating System :: OS Independent
Classifier: Programming Language :: Python :: 3
Requires-Python: >=3.9
Requires-Dist: requests>=2.25.0
Requires-Dist: textual>=5.0.0
